topsis/102217004.py
topsis/__init__.py
TOPSIS_Dishav_102217004-0.6.dist-info/METADATA
TOPSIS_Dishav_102217004-0.6.dist-info/WHEEL
TOPSIS_Dishav_102217004-0.6.dist-info/entry_points.txt
TOPSIS_Dishav_102217004-0.6.dist-info/top_level.txt
TOPSIS_Dishav_102217004-0.6.dist-info/RECORD
