Metadata-Version: 2.1
Name: TOPSIS-Dishav-102217004
Version: 0.6
Summary: A Python package for implementing the TOPSIS decision-making method.
Home-page: https://github.com/DISHAVSINGLA/Topsis_Dishav_102217004
Author: Dishav
Author-email: dsingla2_be22@thapar.edu
Classifier: Programming Language :: Python :: 3
Classifier: License :: OSI Approved :: MIT License
Classifier: Operating System :: OS Independent
Requires-Python: >=3.6
Requires-Dist: numpy
Requires-Dist: pandas
